netcdf_to_csv.py
netcdf_to_csv-1.0.2.dist-info/METADATA
netcdf_to_csv-1.0.2.dist-info/WHEEL
netcdf_to_csv-1.0.2.dist-info/entry_points.txt
netcdf_to_csv-1.0.2.dist-info/top_level.txt
netcdf_to_csv-1.0.2.dist-info/RECORD
