Metadata-Version: 2.1
Name: netcdf-to-csv
Version: 1.0.2
Requires-Dist: netCDF4
